ShutdownApplet/ShutdownApplet.py
ShutdownApplet/__init__.py
ShutdownApplet/resources/__init__.py
ShutdownApplet-0.0.2.dist-info/LICENSE
ShutdownApplet-0.0.2.dist-info/METADATA
ShutdownApplet-0.0.2.dist-info/WHEEL
ShutdownApplet-0.0.2.dist-info/entry_points.txt
ShutdownApplet-0.0.2.dist-info/top_level.txt
ShutdownApplet-0.0.2.dist-info/RECORD
