Metadata-Version: 2.1
Name: ShutdownApplet
Version: 0.0.2
Summary: A Simple GUI to schedule a system shutdown
Home-page: https://github.com/tobiglaser/ShutdownApplet
Author: Tobias Glaser
Classifier: Programming Language :: Python :: 3
Classifier: License :: OSI Approved :: GNU General Public License v2 (GPLv2)
Classifier: Operating System :: POSIX :: Linux
Classifier: Operating System :: Microsoft :: Windows
Classifier: Intended Audience :: End Users/Desktop
Classifier: Topic :: Home Automation
Classifier: Topic :: Utilities
Requires-Python: >=3.10
License-File: LICENSE
